alpinejswidget/__init__.py
alpinejswidget/common.py
alpinejswidget/state.py
alpinejswidget/widget.py
alpinejswidget-0.0.3.dist-info/WHEEL
alpinejswidget-0.0.3.dist-info/METADATA
alpinejswidget-0.0.3.dist-info/RECORD
