Metadata-Version: 2.1
Name: alpinejswidget
Version: 0.0.3
Summary: 
Author: Thiago Cesar
Author-email: k1mbl3@gmail.com
Requires-Python: >=3.7,<4.0
Classifier: Programming Language :: Python :: 3
Classifier: Programming Language :: Python :: 3.7
Classifier: Programming Language :: Python :: 3.8
Classifier: Programming Language :: Python :: 3.9
Classifier: Programming Language :: Python :: 3.10
Classifier: Programming Language :: Python :: 3.11
Requires-Dist: jsbeautifier (>=1.14.7,<2.0.0)
Requires-Dist: pscript (>=0.7.7,<0.8.0)
Requires-Dist: soupwidget (>=0.0.2,<0.0.3)
